camelcaser/__init__.py
camelcaser/word_lists/alpha_words.txt
python_camelcaser-1.0.2.dist-info/METADATA
python_camelcaser-1.0.2.dist-info/WHEEL
python_camelcaser-1.0.2.dist-info/top_level.txt
python_camelcaser-1.0.2.dist-info/RECORD
