Metadata-Version: 2.1
Name: python-camelcaser
Version: 1.0.2
Summary: Convert strings to camel, snake and kebab case - even if separation is unknown.
Home-page: https://github.com/benschaedlich/python-camelcaser
Author: Benjamin Schaedlich
License: UNKNOWN
Project-URL: Documentation, https://github.com/benschaedlich/python-camelcaser
Project-URL: Source, https://github.com/benschaedlich/python-camelcaser
Platform: UNKNOWN
Classifier: Programming Language :: Python :: 3
Classifier: License :: OSI Approved :: MIT License
Classifier: Operating System :: OS Independent
Requires-Dist: pyenchant (==3.2.2)
